advcalc/__init__.py
advcalc/addnumbers.py
myutility_internal-99.0.7.dist-info/METADATA
myutility_internal-99.0.7.dist-info/WHEEL
myutility_internal-99.0.7.dist-info/top_level.txt
myutility_internal-99.0.7.dist-info/RECORD
